simple_crawler/__init__.py
simple_crawler/cli.py
simple_crawler/crawler.py
simple_crawler/hyperlink.py
simple_crawler/parser.py
simple_crawler/requester.py
simple_crawler/url_normalisation.py
tests/__init__.py
tests/conftest.py
tests/test_cli.py
tests/test_crawler.py
tests/test_hyperlink.py
tests/test_parser.py
tests/test_requester.py
SimpleCrawler-1.0.1.dist-info/METADATA
SimpleCrawler-1.0.1.dist-info/WHEEL
SimpleCrawler-1.0.1.dist-info/entry_points.txt
SimpleCrawler-1.0.1.dist-info/top_level.txt
SimpleCrawler-1.0.1.dist-info/RECORD
