Metadata-Version: 2.1
Name: SimpleCrawler
Version: 1.0.1
Summary: Enter something here
Home-page: https://github.com/jackwardell
Author: jackwardell
Author-email: jack@wardell.xyz
License: UNKNOWN
Keywords: python
Platform: UNKNOWN
Classifier: Programming Language :: Python
Classifier: Programming Language :: Python :: 3
Classifier: Programming Language :: Python :: 3.6
Classifier: Programming Language :: Python :: 3.7
Classifier: Programming Language :: Python :: 3.8
Classifier: Programming Language :: Python :: 3.9
Classifier: License :: OSI Approved :: MIT License
Classifier: Operating System :: OS Independent
Classifier: Natural Language :: English
Classifier: Intended Audience :: Developers
Requires-Python: >=3.6
Requires-Dist: requests
Requires-Dist: click
